{"nodes": [{"id": "c_users_opo25_documents_devs_learnlove_bossroom_rooms_lua", "label": "rooms.lua", "file_type": "code", "source_file": "rooms.lua", "source_location": "L1"}, {"id": "bossroom_rooms_rooms_buildworld", "label": "Rooms.buildWorld()", "file_type": "code", "source_file": "rooms.lua", "source_location": "L55"}, {"id": "bossroom_rooms_rooms_sealdoor", "label": "Rooms.sealDoor()", "file_type": "code", "source_file": "rooms.lua", "source_location": "L75"}, {"id": "bossroom_rooms_rooms_unsealdoor", "label": "Rooms.unsealDoor()", "file_type": "code", "source_file": "rooms.lua", "source_location": "L83"}, {"id": "bossroom_rooms_rooms_getroomat", "label": "Rooms.getRoomAt()", "file_type": "code", "source_file": "rooms.lua", "source_location": "L92"}], "edges": [{"source": "c_users_opo25_documents_devs_learnlove_bossroom_rooms_lua", "target": "c_users_opo25_documents_devs_learnlove_bossroom_deps_bump_lua", "relation": "imports", "context": "import", "confidence": "EXTRACTED", "confidence_score": 1.0, "source_file": "rooms.lua", "source_location": "2", "weight": 1.0}, {"source": "c_users_opo25_documents_devs_learnlove_bossroom_rooms_lua", "target": "bossroom_rooms_rooms_buildworld", "relation": "contains", "confidence": "EXTRACTED", "source_file": "rooms.lua", "source_location": "L55", "weight": 1.0}, {"source": "c_users_opo25_documents_devs_learnlove_bossroom_rooms_lua", "target": "bossroom_rooms_rooms_sealdoor", "relation": "contains", "confidence": "EXTRACTED", "source_file": "rooms.lua", "source_location": "L75", "weight": 1.0}, {"source": "c_users_opo25_documents_devs_learnlove_bossroom_rooms_lua", "target": "bossroom_rooms_rooms_unsealdoor", "relation": "contains", "confidence": "EXTRACTED", "source_file": "rooms.lua", "source_location": "L83", "weight": 1.0}, {"source": "c_users_opo25_documents_devs_learnlove_bossroom_rooms_lua", "target": "bossroom_rooms_rooms_getroomat", "relation": "contains", "confidence": "EXTRACTED", "source_file": "rooms.lua", "source_location": "L92", "weight": 1.0}], "raw_calls": [{"caller_nid": "bossroom_rooms_rooms_buildworld", "callee": "bump.newWorld", "is_member_call": false, "source_file": "C:\\Users\\opo25\\Documents\\Devs\\learnlove\\bossroom\\rooms.lua", "source_location": "L56", "receiver": null}, {"caller_nid": "bossroom_rooms_rooms_buildworld", "callee": "pairs", "is_member_call": false, "source_file": "C:\\Users\\opo25\\Documents\\Devs\\learnlove\\bossroom\\rooms.lua", "source_location": "L59", "receiver": null}, {"caller_nid": "bossroom_rooms_rooms_buildworld", "callee": "ipairs", "is_member_call": false, "source_file": "C:\\Users\\opo25\\Documents\\Devs\\learnlove\\bossroom\\rooms.lua", "source_location": "L60", "receiver": null}, {"caller_nid": "bossroom_rooms_rooms_buildworld", "callee": "ipairs", "is_member_call": false, "source_file": "C:\\Users\\opo25\\Documents\\Devs\\learnlove\\bossroom\\rooms.lua", "source_location": "L67", "receiver": null}, {"caller_nid": "bossroom_rooms_rooms_getroomat", "callee": "pairs", "is_member_call": false, "source_file": "C:\\Users\\opo25\\Documents\\Devs\\learnlove\\bossroom\\rooms.lua", "source_location": "L93", "receiver": null}]}